setup.py
distributions_IB/Binomialdistribution.py
distributions_IB/Gaussiandistribution.py
distributions_IB/Generaldistribution.py
distributions_IB/__init__.py
distributions_IB.egg-info/PKG-INFO
distributions_IB.egg-info/SOURCES.txt
distributions_IB.egg-info/dependency_links.txt
distributions_IB.egg-info/not-zip-safe
distributions_IB.egg-info/top_level.txt